msglite/__init__.py
msglite/attachment.py
msglite/constants.py
msglite/encoding.py
msglite/message.py
msglite/prop.py
msglite/properties.py
msglite/recipient.py
msglite/utils.py
msglite-0.30.0.dist-info/LICENSE.txt
msglite-0.30.0.dist-info/METADATA
msglite-0.30.0.dist-info/WHEEL
msglite-0.30.0.dist-info/top_level.txt
msglite-0.30.0.dist-info/RECORD
