Metadata-Version: 2.1
Name: msglite
Version: 0.30.0
Summary: Extracts emails and attachments saved in Microsoft Outlook's .msg files
Home-page: https://github.com/alephdata/msglite
Author: OCCRP
License: GPL
Platform: UNKNOWN
Requires-Dist: olefile (>=0.46)
Requires-Dist: ebcdic (>=1.1.1)
Requires-Dist: compressed-rtf (>=1.0.6)
Requires-Dist: chardet
Requires-Dist: pytz
